fortitude/__init__.py
fortitude/__main__.py
fortitude_lint-0.7.5.data/scripts/fortitude.exe
fortitude_lint-0.7.5.dist-info/METADATA
fortitude_lint-0.7.5.dist-info/WHEEL
fortitude_lint-0.7.5.dist-info/licenses/LICENSE
fortitude_lint-0.7.5.dist-info/RECORD
