Metadata-Version: 2.4
Name: fortitude-lint
Version: 0.7.5
Classifier: Development Status :: 2 - Pre-Alpha
Classifier: Intended Audience :: Developers
Classifier: License :: OSI Approved :: MIT License
Classifier: Natural Language :: English
Classifier: Operating System :: OS Independent
Classifier: Programming Language :: Python
Classifier: Programming Language :: Rust
Classifier: Topic :: Software Development :: Quality Assurance
Requires-Dist: ruff ; extra == 'lint'
Provides-Extra: lint
License-File: LICENSE
Summary: A Fortran linter, written in Rust and installable with Python
Keywords: Fortran,linter
Author-email: Liam Pattinson <liampattinson@gmail.com>, Peter Hill <peter.hill@york.ac.uk>
Requires-Python: >=3.10
Project-URL: Repository, https://github.com/PlasmaFAIR/fortitude
